rdcas/__init__.py
rdcas/main.py
rdconfig/__init__.py
rdconfig/config.py
rdconfig/glb.py
rdconfig/global.py
rdconfig/private.py
rdconfig/protect.py
rdcrm/__init__.py
rdcrm/customer.py
rdcrm/login.py
rdcrm/product.py
rdcrm/salesOrder.py
rdcrm/bill/__init__.py
rdcrm/bill/salesOrder.py
rdcrm/md/__init__.py
rdcrm/md/customer.py
rdcrm/md/product.py
rdcas-1.0.2.dist-info/LICENSE
rdcas-1.0.2.dist-info/METADATA
rdcas-1.0.2.dist-info/WHEEL
rdcas-1.0.2.dist-info/top_level.txt
rdcas-1.0.2.dist-info/RECORD
