Metadata-Version: 2.1
Name: rdcas
Version: 1.0.2
Summary: cash management system for rds 
Home-page: http://www.reshapedata.com
Author: hulilei
Author-email: hulilei@takewiki.com.cn
License: Apache License
Keywords: reshapedata,rdcas
Platform: UNKNOWN
Requires-Python: >=3.6
License-File: LICENSE
Requires-Dist: requests
